MANIFEST.in
README.md
setup.py
Gallimaufry/Colorer.py
Gallimaufry/Configuration.py
Gallimaufry/Device.py
Gallimaufry/Endpoint.py
Gallimaufry/HID.py
Gallimaufry/Interface.py
Gallimaufry/USB.py
Gallimaufry/UVC.py
Gallimaufry/Version.py
Gallimaufry/__init__.py
Gallimaufry/helpers.py
Gallimaufry/settings.py
Gallimaufry/usb.ids
Gallimaufry/Classes/__init__.py
Gallimaufry/Classes/HID/Keyboard.py
Gallimaufry/Classes/HID/Mouse.py
Gallimaufry/Classes/HID/__init__.py
gallimaufry.egg-info/PKG-INFO
gallimaufry.egg-info/SOURCES.txt
gallimaufry.egg-info/dependency_links.txt
gallimaufry.egg-info/requires.txt
gallimaufry.egg-info/top_level.txt