Metadata-Version: 2.1
Name: gallimaufry
Version: 0.0.4
Summary: Tool to ease parsing of USB information out of pcaps
Home-page: https://github.com/bannsec/gallimaufry
Author: Michael Bann
Author-email: self@bannsecurity.com
License: MIT
Keywords: usb pcap parse
Platform: UNKNOWN
Classifier: Development Status :: 3 - Alpha
Classifier: Intended Audience :: End Users/Desktop
Classifier: License :: OSI Approved :: MIT License
Classifier: Programming Language :: Python :: 3
Classifier: Operating System :: POSIX :: Linux
Classifier: Environment :: Console
Provides-Extra: dev
